nrt_threads_utils/__init__.py
nrt_threads_utils/threads_pool_manager/__init__.py
nrt_threads_utils/threads_pool_manager/enums.py
nrt_threads_utils/threads_pool_manager/metrics.py
nrt_threads_utils/threads_pool_manager/tasks.py
nrt_threads_utils/threads_pool_manager/threads_pool_manager.py
nrt_threads_utils/threads_pool_manager/threads_pool_manager_exceptions.py
nrt_threads_utils-2.1.2.data/data/requirements.txt
nrt_threads_utils-2.1.2.dist-info/licenses/LICENSE
tests/threads_pool_manager/__init__.py
tests/threads_pool_manager/threads_pool_manager_test.py
tests/threads_pool_manager/threads_pool_manager_test_base.py
tests/threads_pool_manager/performance/__init__.py
tests/threads_pool_manager/performance/performance_base.py
tests/threads_pool_manager/performance/soak.py
tests/threads_pool_manager/performance/threads_pool_manager_performance_test.py
nrt_threads_utils-2.1.2.dist-info/METADATA
nrt_threads_utils-2.1.2.dist-info/WHEEL
nrt_threads_utils-2.1.2.dist-info/top_level.txt
nrt_threads_utils-2.1.2.dist-info/RECORD
