Metadata-Version: 2.4
Name: nrt-threads-utils
Version: 2.1.2
Summary: Threads utilities in Python
Home-page: https://github.com/etuzon/python-nrt-threads-utils
Author: Eyal Tuzon
Author-email: Eyal Tuzon <eyal.tuzon.dev@gmail.com>
Project-URL: Homepage, https://github.com/etuzon/python-nrt-threads-utils
Project-URL: Bug Tracker, https://github.com/etuzon/python-nrt-threads-utils/issues
Project-URL: documentation, https://github.com/etuzon/python-nrt-threads-utils/wiki
Keywords: python,python3,python-3,tool,tools,thread,threads,pool,threads-pool,util,nrt,nrt-utils,nrt-utilities,threads-utils,threads-utilities,nrt-utilities,nrt-threads-utils,nrt-threads-utilities
Classifier: Programming Language :: Python :: 3
Classifier: Programming Language :: Python :: 3.8
Classifier: Programming Language :: Python :: 3.9
Classifier: Programming Language :: Python :: 3.10
Classifier: Programming Language :: Python :: 3.11
Classifier: Programming Language :: Python :: 3.12
Classifier: Programming Language :: Python :: 3.13
Classifier: Programming Language :: Python :: 3.14
Classifier: Operating System :: OS Independent
Requires-Python: >=3.8
License-File: LICENSE
Requires-Dist: nrt-collections-utils>=1.0.0
Requires-Dist: nrt-time-utils>=1.0.4
Dynamic: author
Dynamic: home-page
Dynamic: license-file
Dynamic: requires-dist
